setup.cfg
setup.py
idcheckio_python_client/__init__.py
idcheckio_python_client/api_client.py
idcheckio_python_client/configuration.py
idcheckio_python_client/rest.py
idcheckio_python_client.egg-info/PKG-INFO
idcheckio_python_client.egg-info/SOURCES.txt
idcheckio_python_client.egg-info/dependency_links.txt
idcheckio_python_client.egg-info/requires.txt
idcheckio_python_client.egg-info/top_level.txt
idcheckio_python_client/apis/__init__.py
idcheckio_python_client/apis/administration_api.py
idcheckio_python_client/apis/analysis_api.py
idcheckio_python_client/apis/sandbox_api.py
idcheckio_python_client/models/__init__.py
idcheckio_python_client/models/check_summary_of_the_submitted_document.py
idcheckio_python_client/models/classification_of_the_submitted_document.py
idcheckio_python_client/models/control.py
idcheckio_python_client/models/control_group.py
idcheckio_python_client/models/detailed_information_of_the_holder_of_the_submitted_document.py
idcheckio_python_client/models/detailed_information_of_the_submitted_document.py
idcheckio_python_client/models/error_response.py
idcheckio_python_client/models/event_date.py
idcheckio_python_client/models/extracted_image.py
idcheckio_python_client/models/generic_data.py
idcheckio_python_client/models/health_response.py
idcheckio_python_client/models/image.py
idcheckio_python_client/models/image_indicator.py
idcheckio_python_client/models/image_list_response.py
idcheckio_python_client/models/image_request.py
idcheckio_python_client/models/mrz.py
idcheckio_python_client/models/mrz_list_response.py
idcheckio_python_client/models/mrz_request.py
idcheckio_python_client/models/mrz_response.py
idcheckio_python_client/models/report_response.py
idcheckio_python_client/models/result_response.py
idcheckio_python_client/models/task_response.py
idcheckio_python_client/models/user_response.py
test/__init__.py
test/test_administration_api.py
test/test_analysis_api.py
test/test_check_summary_of_the_submitted_document.py
test/test_classification_of_the_submitted_document.py
test/test_control.py
test/test_control_group.py
test/test_detailed_information_of_the_holder_of_the_submitted_document.py
test/test_detailed_information_of_the_submitted_document.py
