Metadata-Version: 1.0
Name: idcheckio-python-client
Version: 1.0.0
Summary: IdCheck.IO API
Home-page: https://www.idcheck.io
Author: UNKNOWN
Author-email: dev@ariadnext.com
License: UNKNOWN
Keywords: Swagger,IdCheck.IO API,idcheckio,id,verifications,passport,verification,visa,driving,licence,permit,de,sejour,passeport,carte,d'identite
Platform: UNKNOWN
